remarkdav/__init__.py
remarkdav/cli.py
remarkdav/config.py
remarkdav/crawl.py
remarkdav/pdf.py
remarkdav/rmapy_util.py
remarkdav/sync_db.py
remarkdav/utils.py
remarkdav-1.0.3.dist-info/entry_points.txt
remarkdav-1.0.3.dist-info/LICENSE
remarkdav-1.0.3.dist-info/WHEEL
remarkdav-1.0.3.dist-info/METADATA
remarkdav-1.0.3.dist-info/RECORD
